docker_storage/__init__.py
docker_storage/cli.py
docker_storage/driver.py
docker_storage-0.0.1.dist-info/DESCRIPTION.rst
docker_storage-0.0.1.dist-info/entry_points.txt
docker_storage-0.0.1.dist-info/METADATA
docker_storage-0.0.1.dist-info/metadata.json
docker_storage-0.0.1.dist-info/RECORD
docker_storage-0.0.1.dist-info/top_level.txt
docker_storage-0.0.1.dist-info/WHEEL
