Metadata-Version: 2.0
Name: docker-storage
Version: 0.0.1
Summary: Utilities to work with docker data containers
Home-page: https://github.com/GaretJax/docker-storage
Author: Jonathan Stoppani
Author-email: jonathan@stoppani.name
License: MIT
Platform: UNKNOWN
Classifier: Development Status :: 4 - Beta
Classifier: Intended Audience :: Developers
Classifier: License :: OSI Approved :: MIT License
Classifier: Operating System :: OS Independent
Classifier: Programming Language :: Python
Classifier: Programming Language :: Python :: 2.7
Classifier: Programming Language :: Python :: 3
Classifier: Programming Language :: Python :: 3.3
Classifier: Programming Language :: Python :: 3.4
Requires-Dist: click (>=4)
Requires-Dist: docker-py (>=1.4)
Requires-Dist: requests (==2.7.0)
Requires-Dist: six (==1.9.0)
Requires-Dist: websocket-client (==0.32.0)
Requires-Dist: tabulate (==0.7.5)
